Metadata-Version: 1.0
Name: masonite-sparkpost-driver
Version: 0.0.1
Summary: Sparkpost mail driver for the Masonite framework
Home-page: https://github.com/bjorntheart/masonite-sparkpost-driver
Author: Bjorn Theart
Author-email: bjorntheart@gmail.com
License: UNKNOWN
Keywords: python web framework,python3,masonite,sparkpost
Platform: UNKNOWN
